cartoonfight/__init__.py
cartoonfight/__main__.py
cartoonfight/player.py
cartoonfight/prepare.py
cartoonfight/start.py
cartoonfight/tools.py
cartoonfight/images/aang/GL0.png
cartoonfight/images/aang/GL1.png
cartoonfight/images/aang/GL10.png
cartoonfight/images/aang/GL11.png
cartoonfight/images/aang/GL12.png
cartoonfight/images/aang/GL13.png
cartoonfight/images/aang/GL2.png
cartoonfight/images/aang/GL3.png
cartoonfight/images/aang/GL4.png
cartoonfight/images/aang/GL5.png
cartoonfight/images/aang/GL6.png
cartoonfight/images/aang/GL7.png
cartoonfight/images/aang/GL8.png
cartoonfight/images/aang/GL9.png
cartoonfight/images/aang/GR0.png
cartoonfight/images/aang/GR1.png
cartoonfight/images/aang/GR10.png
cartoonfight/images/aang/GR11.png
cartoonfight/images/aang/GR12.png
cartoonfight/images/aang/GR13.png
cartoonfight/images/aang/GR2.png
cartoonfight/images/aang/GR3.png
cartoonfight/images/aang/GR4.png
cartoonfight/images/aang/GR5.png
cartoonfight/images/aang/GR6.png
cartoonfight/images/aang/GR7.png
cartoonfight/images/aang/GR8.png
cartoonfight/images/aang/GR9.png
cartoonfight/images/aang/KL0.png
cartoonfight/images/aang/KL1.png
cartoonfight/images/aang/KL2.png
cartoonfight/images/aang/KL3.png
cartoonfight/images/aang/KR0.png
cartoonfight/images/aang/KR1.png
cartoonfight/images/aang/KR2.png
cartoonfight/images/aang/KR3.png
cartoonfight/images/aang/WL0.png
cartoonfight/images/aang/WL1.png
cartoonfight/images/aang/WL2.png
cartoonfight/images/aang/WL3.png
cartoonfight/images/aang/WL4.png
cartoonfight/images/aang/WR0.png
cartoonfight/images/aang/WR1.png
cartoonfight/images/aang/WR2.png
cartoonfight/images/aang/WR3.png
cartoonfight/images/aang/WR4.png
cartoonfight/images/backgrounds/default.jpg
cartoonfight/images/goblin/PL0.png
cartoonfight/images/goblin/PL1.png
cartoonfight/images/goblin/PL2.png
cartoonfight/images/goblin/PR0.png
cartoonfight/images/goblin/PR1.png
cartoonfight/images/goblin/PR2.png
cartoonfight/images/goblin/WL0.png
cartoonfight/images/goblin/WL1.png
cartoonfight-1.0.dev23.dist-info/LICENSE
cartoonfight-1.0.dev23.dist-info/METADATA
cartoonfight-1.0.dev23.dist-info/WHEEL
cartoonfight-1.0.dev23.dist-info/entry_points.txt
cartoonfight-1.0.dev23.dist-info/top_level.txt
cartoonfight-1.0.dev23.dist-info/RECORD
