Metadata-Version: 2.1
Name: cartoonfight
Version: 1.0.dev23
Summary: 2D Fighting game with cartoon characters
Home-page: https://github.com/kmmelcher/cartoonfight
Author: Kilian Melcher
Author-email: kilian.melcher@gmail.com
License: UNKNOWN
Platform: UNKNOWN
Classifier: Development Status :: 1 - Planning
Classifier: Programming Language :: Python :: 3
Classifier: License :: OSI Approved :: MIT License
Classifier: Operating System :: Unix
Requires-Python: >=3.6
Requires-Dist: pygame (>=2.0)
